odoo/addons/report_xlsx_helper_demo/README.rst
odoo/addons/report_xlsx_helper_demo/__init__.py
odoo/addons/report_xlsx_helper_demo/__manifest__.py
odoo/addons/report_xlsx_helper_demo/i18n/es.po
odoo/addons/report_xlsx_helper_demo/i18n/it.po
odoo/addons/report_xlsx_helper_demo/i18n/report_xlsx_helper_demo.pot
odoo/addons/report_xlsx_helper_demo/models/__init__.py
odoo/addons/report_xlsx_helper_demo/models/res_partner.py
odoo/addons/report_xlsx_helper_demo/readme/CONTRIBUTORS.rst
odoo/addons/report_xlsx_helper_demo/readme/DESCRIPTION.rst
odoo/addons/report_xlsx_helper_demo/readme/INSTALL.rst
odoo/addons/report_xlsx_helper_demo/readme/USAGE.rst
odoo/addons/report_xlsx_helper_demo/report/__init__.py
odoo/addons/report_xlsx_helper_demo/report/partner_export_xlsx.py
odoo/addons/report_xlsx_helper_demo/static/description/icon.png
odoo/addons/report_xlsx_helper_demo/static/description/index.html
odoo/addons/report_xlsx_helper_demo/views/res_partner.xml
odoo14_addon_report_xlsx_helper_demo-14.0.1.0.1.dev8.dist-info/METADATA
odoo14_addon_report_xlsx_helper_demo-14.0.1.0.1.dev8.dist-info/WHEEL
odoo14_addon_report_xlsx_helper_demo-14.0.1.0.1.dev8.dist-info/top_level.txt
odoo14_addon_report_xlsx_helper_demo-14.0.1.0.1.dev8.dist-info/RECORD
